[
  {
    "inputs": [
      {
        "internalType": "address",
        "name": "_pompHub",
        "type": "address"
      },
      {
        "internalType": "address",
        "name": "_missionNFT",
        "type": "address"
      }
    ],
    "stateMutability": "nonpayable",
    "type": "constructor"
  },
  {
    "anonymous": false,
    "inputs": [
      {
        "indexed": true,
        "internalType": "uint256",
        "name": "profileId",
        "type": "uint256"
      },
      {
        "indexed": true,
        "internalType": "uint256",
        "name": "missionId",
        "type": "uint256"
      },
      {
        "indexed": false,
        "internalType": "uint256",
        "name": "timestamp",
        "type": "uint256"
      }
    ],
    "name": "Aborted",
    "type": "event"
  },
  {
    "anonymous": false,
    "inputs": [
      {
        "indexed": true,
        "internalType": "address",
        "name": "verifier",
        "type": "address"
      },
      {
        "indexed": true,
        "internalType": "uint256",
        "name": "count",
        "type": "uint256"
      },
      {
        "indexed": false,
        "internalType": "uint256",
        "name": "timestamp",
        "type": "uint256"
      }
    ],
    "name": "BatchVerified",
    "type": "event"
  },
  {
    "anonymous": false,
    "inputs": [
      {
        "indexed": true,
        "internalType": "address",
        "name": "verifier",
        "type": "address"
      },
      {
        "indexed": true,
        "internalType": "uint256",
        "name": "profileId",
        "type": "uint256"
      },
      {
        "indexed": true,
        "internalType": "uint256",
        "name": "missionId",
        "type": "uint256"
      },
      {
        "indexed": false,
        "internalType": "bytes32",
        "name": "challenge",
        "type": "bytes32"
      },
      {
        "indexed": false,
        "internalType": "uint256",
        "name": "timestamp",
        "type": "uint256"
      }
    ],
    "name": "Completed",
    "type": "event"
  },
  {
    "anonymous": false,
    "inputs": [
      {
        "indexed": true,
        "internalType": "address",
        "name": "verifier",
        "type": "address"
      },
      {
        "indexed": true,
        "internalType": "uint256",
        "name": "profileId",
        "type": "uint256"
      },
      {
        "indexed": true,
        "internalType": "uint256",
        "name": "missionId",
        "type": "uint256"
      },
      {
        "indexed": false,
        "internalType": "bytes32",
        "name": "challenge",
        "type": "bytes32"
      },
      {
        "indexed": false,
        "internalType": "uint256",
        "name": "reason",
        "type": "uint256"
      },
      {
        "indexed": false,
        "internalType": "uint256",
        "name": "timestamp",
        "type": "uint256"
      }
    ],
    "name": "Failed",
    "type": "event"
  },
  {
    "anonymous": false,
    "inputs": [
      {
        "indexed": true,
        "internalType": "bytes32",
        "name": "role",
        "type": "bytes32"
      },
      {
        "indexed": true,
        "internalType": "bytes32",
        "name": "previousAdminRole",
        "type": "bytes32"
      },
      {
        "indexed": true,
        "internalType": "bytes32",
        "name": "newAdminRole",
        "type": "bytes32"
      }
    ],
    "name": "RoleAdminChanged",
    "type": "event"
  },
  {
    "anonymous": false,
    "inputs": [
      {
        "indexed": true,
        "internalType": "bytes32",
        "name": "role",
        "type": "bytes32"
      },
      {
        "indexed": true,
        "internalType": "address",
        "name": "account",
        "type": "address"
      },
      {
        "indexed": true,
        "internalType": "address",
        "name": "sender",
        "type": "address"
      }
    ],
    "name": "RoleGranted",
    "type": "event"
  },
  {
    "anonymous": false,
    "inputs": [
      {
        "indexed": true,
        "internalType": "bytes32",
        "name": "role",
        "type": "bytes32"
      },
      {
        "indexed": true,
        "internalType": "address",
        "name": "account",
        "type": "address"
      },
      {
        "indexed": true,
        "internalType": "address",
        "name": "sender",
        "type": "address"
      }
    ],
    "name": "RoleRevoked",
    "type": "event"
  },
  {
    "anonymous": false,
    "inputs": [
      {
        "indexed": true,
        "internalType": "address",
        "name": "creator",
        "type": "address"
      },
      {
        "indexed": true,
        "internalType": "uint256",
        "name": "profileId",
        "type": "uint256"
      },
      {
        "indexed": true,
        "internalType": "uint256",
        "name": "missionId",
        "type": "uint256"
      },
      {
        "indexed": false,
        "internalType": "uint256",
        "name": "endtime",
        "type": "uint256"
      },
      {
        "indexed": false,
        "internalType": "uint256",
        "name": "timestamp",
        "type": "uint256"
      }
    ],
    "name": "Started",
    "type": "event"
  },
  {
    "anonymous": false,
    "inputs": [
      {
        "indexed": true,
        "internalType": "address",
        "name": "verifier",
        "type": "address"
      },
      {
        "indexed": true,
        "internalType": "uint256",
        "name": "profileId",
        "type": "uint256"
      },
      {
        "indexed": true,
        "internalType": "uint256",
        "name": "missionId",
        "type": "uint256"
      },
      {
        "indexed": false,
        "internalType": "bytes32",
        "name": "challenge",
        "type": "bytes32"
      },
      {
        "indexed": false,
        "internalType": "uint256",
        "name": "timestamp",
        "type": "uint256"
      }
    ],
    "name": "Verified",
    "type": "event"
  },
  {
    "inputs": [],
    "name": "DEFAULT_ADMIN_ROLE",
    "outputs": [
      {
        "internalType": "bytes32",
        "name": "",
        "type": "bytes32"
      }
    ],
    "stateMutability": "view",
    "type": "function"
  },
  {
    "inputs": [],
    "name": "HUB_ROLE",
    "outputs": [
      {
        "internalType": "bytes32",
        "name": "",
        "type": "bytes32"
      }
    ],
    "stateMutability": "view",
    "type": "function"
  },
  {
    "inputs": [
      {
        "components": [
          {
            "internalType": "uint256",
            "name": "profileId",
            "type": "uint256"
          },
          {
            "internalType": "uint256",
            "name": "missionId",
            "type": "uint256"
          },
          {
            "internalType": "bytes",
            "name": "signature",
            "type": "bytes"
          },
          {
            "internalType": "uint256",
            "name": "deadline",
            "type": "uint256"
          }
        ],
        "internalType": "struct DataTypes.AbortWithSigData",
        "name": "vars",
        "type": "tuple"
      },
      {
        "internalType": "address",
        "name": "owner",
        "type": "address"
      }
    ],
    "name": "abortWithSig",
    "outputs": [],
    "stateMutability": "nonpayable",
    "type": "function"
  },
  {
    "inputs": [
      {
        "components": [
          {
            "internalType": "uint256[]",
            "name": "profileIds",
            "type": "uint256[]"
          },
          {
            "internalType": "string",
            "name": "challenges",
            "type": "string"
          },
          {
            "internalType": "bytes",
            "name": "signature",
            "type": "bytes"
          },
          {
            "internalType": "uint256",
            "name": "deadline",
            "type": "uint256"
          }
        ],
        "internalType": "struct DataTypes.BatchVerifyWithSigData",
        "name": "vars",
        "type": "tuple"
      },
      {
        "internalType": "address",
        "name": "sender",
        "type": "address"
      }
    ],
    "name": "batchVerifyWithSig",
    "outputs": [],
    "stateMutability": "nonpayable",
    "type": "function"
  },
  {
    "inputs": [
      {
        "components": [
          {
            "internalType": "uint256[]",
            "name": "profileIds",
            "type": "uint256[]"
          },
          {
            "internalType": "string",
            "name": "challenges",
            "type": "string"
          }
        ],
        "internalType": "struct DataTypes.CanBatchVerifyData",
        "name": "vars",
        "type": "tuple"
      },
      {
        "internalType": "address",
        "name": "sender",
        "type": "address"
      }
    ],
    "name": "canBatchVerify",
    "outputs": [
      {
        "internalType": "bool",
        "name": "",
        "type": "bool"
      }
    ],
    "stateMutability": "view",
    "type": "function"
  },
  {
    "inputs": [
      {
        "components": [
          {
            "internalType": "uint256",
            "name": "profileId",
            "type": "uint256"
          },
          {
            "internalType": "uint256",
            "name": "missionId",
            "type": "uint256"
          },
          {
            "internalType": "string",
            "name": "challenge",
            "type": "string"
          },
          {
            "internalType": "bytes",
            "name": "signature",
            "type": "bytes"
          },
          {
            "internalType": "uint256",
            "name": "deadline",
            "type": "uint256"
          }
        ],
        "internalType": "struct DataTypes.CompleteWithSigData",
        "name": "vars",
        "type": "tuple"
      },
      {
        "internalType": "address",
        "name": "owner",
        "type": "address"
      }
    ],
    "name": "completeWithSig",
    "outputs": [],
    "stateMutability": "nonpayable",
    "type": "function"
  },
  {
    "inputs": [
      {
        "components": [
          {
            "internalType": "uint256",
            "name": "profileId",
            "type": "uint256"
          },
          {
            "internalType": "string",
            "name": "challenge",
            "type": "string"
          },
          {
            "internalType": "uint256",
            "name": "reason",
            "type": "uint256"
          },
          {
            "internalType": "bytes",
            "name": "signature",
            "type": "bytes"
          },
          {
            "internalType": "uint256",
            "name": "deadline",
            "type": "uint256"
          }
        ],
        "internalType": "struct DataTypes.FailWithSigData",
        "name": "vars",
        "type": "tuple"
      },
      {
        "internalType": "address",
        "name": "sender",
        "type": "address"
      }
    ],
    "name": "failWithSig",
    "outputs": [],
    "stateMutability": "nonpayable",
    "type": "function"
  },
  {
    "inputs": [
      {
        "internalType": "bytes32",
        "name": "role",
        "type": "bytes32"
      }
    ],
    "name": "getRoleAdmin",
    "outputs": [
      {
        "internalType": "bytes32",
        "name": "",
        "type": "bytes32"
      }
    ],
    "stateMutability": "view",
    "type": "function"
  },
  {
    "inputs": [
      {
        "internalType": "bytes32",
        "name": "role",
        "type": "bytes32"
      },
      {
        "internalType": "address",
        "name": "account",
        "type": "address"
      }
    ],
    "name": "grantRole",
    "outputs": [],
    "stateMutability": "nonpayable",
    "type": "function"
  },
  {
    "inputs": [
      {
        "internalType": "bytes32",
        "name": "role",
        "type": "bytes32"
      },
      {
        "internalType": "address",
        "name": "account",
        "type": "address"
      }
    ],
    "name": "hasRole",
    "outputs": [
      {
        "internalType": "bool",
        "name": "",
        "type": "bool"
      }
    ],
    "stateMutability": "view",
    "type": "function"
  },
  {
    "inputs": [
      {
        "internalType": "string",
        "name": "challenge",
        "type": "string"
      }
    ],
    "name": "missionByChallenge",
    "outputs": [
      {
        "components": [
          {
            "internalType": "address",
            "name": "owner",
            "type": "address"
          },
          {
            "internalType": "uint256",
            "name": "profileId",
            "type": "uint256"
          },
          {
            "internalType": "uint256",
            "name": "tokenId",
            "type": "uint256"
          },
          {
            "internalType": "address",
            "name": "verifier",
            "type": "address"
          },
          {
            "internalType": "uint256",
            "name": "starttime",
            "type": "uint256"
          },
          {
            "internalType": "uint256",
            "name": "endtime",
            "type": "uint256"
          },
          {
            "internalType": "bytes32",
            "name": "challengeHash",
            "type": "bytes32"
          },
          {
            "internalType": "enum DataTypes.State",
            "name": "state",
            "type": "uint8"
          },
          {
            "internalType": "address",
            "name": "creator",
            "type": "address"
          }
        ],
        "internalType": "struct DataTypes.MissionStruct",
        "name": "",
        "type": "tuple"
      },
      {
        "internalType": "uint256",
        "name": "",
        "type": "uint256"
      },
      {
        "internalType": "string",
        "name": "",
        "type": "string"
      }
    ],
    "stateMutability": "view",
    "type": "function"
  },
  {
    "inputs": [
      {
        "internalType": "uint256",
        "name": "profileId",
        "type": "uint256"
      },
      {
        "internalType": "uint256",
        "name": "missionId",
        "type": "uint256"
      }
    ],
    "name": "missionById",
    "outputs": [
      {
        "components": [
          {
            "internalType": "address",
            "name": "owner",
            "type": "address"
          },
          {
            "internalType": "uint256",
            "name": "profileId",
            "type": "uint256"
          },
          {
            "internalType": "uint256",
            "name": "tokenId",
            "type": "uint256"
          },
          {
            "internalType": "address",
            "name": "verifier",
            "type": "address"
          },
          {
            "internalType": "uint256",
            "name": "starttime",
            "type": "uint256"
          },
          {
            "internalType": "uint256",
            "name": "endtime",
            "type": "uint256"
          },
          {
            "internalType": "bytes32",
            "name": "challengeHash",
            "type": "bytes32"
          },
          {
            "internalType": "enum DataTypes.State",
            "name": "state",
            "type": "uint8"
          },
          {
            "internalType": "address",
            "name": "creator",
            "type": "address"
          }
        ],
        "internalType": "struct DataTypes.MissionStruct",
        "name": "",
        "type": "tuple"
      },
      {
        "internalType": "uint256",
        "name": "",
        "type": "uint256"
      },
      {
        "internalType": "string",
        "name": "",
        "type": "string"
      }
    ],
    "stateMutability": "view",
    "type": "function"
  },
  {
    "inputs": [
      {
        "internalType": "uint256",
        "name": "profileId",
        "type": "uint256"
      },
      {
        "internalType": "string",
        "name": "slug",
        "type": "string"
      }
    ],
    "name": "missionBySlug",
    "outputs": [
      {
        "components": [
          {
            "internalType": "address",
            "name": "owner",
            "type": "address"
          },
          {
            "internalType": "uint256",
            "name": "profileId",
            "type": "uint256"
          },
          {
            "internalType": "uint256",
            "name": "tokenId",
            "type": "uint256"
          },
          {
            "internalType": "address",
            "name": "verifier",
            "type": "address"
          },
          {
            "internalType": "uint256",
            "name": "starttime",
            "type": "uint256"
          },
          {
            "internalType": "uint256",
            "name": "endtime",
            "type": "uint256"
          },
          {
            "internalType": "bytes32",
            "name": "challengeHash",
            "type": "bytes32"
          },
          {
            "internalType": "enum DataTypes.State",
            "name": "state",
            "type": "uint8"
          },
          {
            "internalType": "address",
            "name": "creator",
            "type": "address"
          }
        ],
        "internalType": "struct DataTypes.MissionStruct",
        "name": "",
        "type": "tuple"
      }
    ],
    "stateMutability": "view",
    "type": "function"
  },
  {
    "inputs": [
      {
        "internalType": "string",
        "name": "slug",
        "type": "string"
      }
    ],
    "name": "missionIdBySlug",
    "outputs": [
      {
        "internalType": "uint256",
        "name": "",
        "type": "uint256"
      }
    ],
    "stateMutability": "view",
    "type": "function"
  },
  {
    "inputs": [],
    "name": "missionNFT",
    "outputs": [
      {
        "internalType": "address",
        "name": "",
        "type": "address"
      }
    ],
    "stateMutability": "view",
    "type": "function"
  },
  {
    "inputs": [
      {
        "internalType": "address",
        "name": "",
        "type": "address"
      },
      {
        "internalType": "address",
        "name": "",
        "type": "address"
      },
      {
        "internalType": "uint256",
        "name": "",
        "type": "uint256"
      },
      {
        "internalType": "bytes",
        "name": "",
        "type": "bytes"
      }
    ],
    "name": "onERC721Received",
    "outputs": [
      {
        "internalType": "bytes4",
        "name": "",
        "type": "bytes4"
      }
    ],
    "stateMutability": "nonpayable",
    "type": "function"
  },
  {
    "inputs": [],
    "name": "pompHub",
    "outputs": [
      {
        "internalType": "address",
        "name": "",
        "type": "address"
      }
    ],
    "stateMutability": "view",
    "type": "function"
  },
  {
    "inputs": [
      {
        "internalType": "bytes32",
        "name": "role",
        "type": "bytes32"
      },
      {
        "internalType": "address",
        "name": "account",
        "type": "address"
      }
    ],
    "name": "renounceRole",
    "outputs": [],
    "stateMutability": "nonpayable",
    "type": "function"
  },
  {
    "inputs": [
      {
        "internalType": "bytes32",
        "name": "role",
        "type": "bytes32"
      },
      {
        "internalType": "address",
        "name": "account",
        "type": "address"
      }
    ],
    "name": "revokeRole",
    "outputs": [],
    "stateMutability": "nonpayable",
    "type": "function"
  },
  {
    "inputs": [
      {
        "internalType": "address",
        "name": "",
        "type": "address"
      }
    ],
    "name": "sigNonces",
    "outputs": [
      {
        "internalType": "uint256",
        "name": "",
        "type": "uint256"
      }
    ],
    "stateMutability": "view",
    "type": "function"
  },
  {
    "inputs": [
      {
        "components": [
          {
            "internalType": "uint256",
            "name": "profileId",
            "type": "uint256"
          },
          {
            "internalType": "string",
            "name": "slug",
            "type": "string"
          },
          {
            "internalType": "string",
            "name": "contentURI",
            "type": "string"
          },
          {
            "internalType": "uint256",
            "name": "minutesToExpire",
            "type": "uint256"
          },
          {
            "internalType": "address",
            "name": "creator",
            "type": "address"
          },
          {
            "internalType": "address",
            "name": "verifier",
            "type": "address"
          },
          {
            "internalType": "bytes",
            "name": "signature",
            "type": "bytes"
          },
          {
            "internalType": "uint256",
            "name": "deadline",
            "type": "uint256"
          }
        ],
        "internalType": "struct DataTypes.StartWithSigData",
        "name": "vars",
        "type": "tuple"
      },
      {
        "internalType": "address",
        "name": "owner",
        "type": "address"
      }
    ],
    "name": "startWithSig",
    "outputs": [
      {
        "internalType": "uint256",
        "name": "",
        "type": "uint256"
      }
    ],
    "stateMutability": "nonpayable",
    "type": "function"
  },
  {
    "inputs": [
      {
        "internalType": "bytes4",
        "name": "interfaceId",
        "type": "bytes4"
      }
    ],
    "name": "supportsInterface",
    "outputs": [
      {
        "internalType": "bool",
        "name": "",
        "type": "bool"
      }
    ],
    "stateMutability": "view",
    "type": "function"
  },
  {
    "inputs": [
      {
        "components": [
          {
            "internalType": "uint256",
            "name": "profileId",
            "type": "uint256"
          },
          {
            "internalType": "string",
            "name": "challenge",
            "type": "string"
          },
          {
            "internalType": "bytes",
            "name": "signature",
            "type": "bytes"
          },
          {
            "internalType": "uint256",
            "name": "deadline",
            "type": "uint256"
          }
        ],
        "internalType": "struct DataTypes.VerifyWithSigData",
        "name": "vars",
        "type": "tuple"
      },
      {
        "internalType": "address",
        "name": "sender",
        "type": "address"
      }
    ],
    "name": "verifyWithSig",
    "outputs": [],
    "stateMutability": "nonpayable",
    "type": "function"
  }
]
